{"_id":{"$oid":"a9c8c9e1e38866e0c59de7d5"},"employeeID":"1FT7W2A63EE155936","name":"Muriel Boobier"}
{"_id":{"$oid":"e54e580c5da9d2e095d66e34"},"employeeID":"19UUA9F57EA273185","name":"Emelen Linggard"}
{"_id":{"$oid":"a2de8ed6836abcad560e291c"},"employeeID":"1GTN1UEH5EZ431347","name":"Sandra Shatliffe"}
{"_id":{"$oid":"4c18c3eb457f0c558bcdc71b"},"employeeID":"KM8JT3AB4DU570090","name":"Sax Simao"}
{"_id":{"$oid":"19ef9eabe6f2095bf2008b94"},"employeeID":"1FMJK2A57AE966525","name":"Miquela Janczewski"}
{"_id":{"$oid":"b9d42e31b0aaf41609b36b8f"},"employeeID":"3C3CFFAR1FT419504","name":"Peirce Matveyev"}
{"_id":{"$oid":"4d0aa2dc0e11ca7dd94f3cb3"},"employeeID":"1G6AL5S31D0564457","name":"Tedman Pigeram"}
{"_id":{"$oid":"9f2e61f86f3960a0da577d0c"},"employeeID":"SCFBB03B28G310378","name":"Kissie Swanne"}
{"_id":{"$oid":"ed44d9bc060ca37afa46c5e0"},"employeeID":"WA1AM94L19D066266","name":"Darn Impy"}
{"_id":{"$oid":"1547aa70cec5cb6af8b3c8ac"},"employeeID":"WAUNF98P78A970120","name":"Tara Briscoe"}
{"_id":{"$oid":"a290b91d3144580b4d36f9ed"},"employeeID":"WAUR4AFD5CN950953","name":"Tarrah Marchment"}
{"_id":{"$oid":"e30a2c91dc418fd91c54acfb"},"employeeID":"JM3TB2BA2F0203433","name":"Dyane Dunkirk"}
{"_id":{"$oid":"d8037115a4393ff06f148b7c"},"employeeID":"4USBU33528L588221","name":"Talya Chaffe"}
{"_id":{"$oid":"b62f6c7669105b0d5aa8cc0a"},"employeeID":"SCFFDAAE0BG386204","name":"Dilly Boise"}
{"_id":{"$oid":"55077cf6a3b39be9849befec"},"employeeID":"KMHTC6AD1EU557598","name":"Neila Woodger"}
{"_id":{"$oid":"45ca534d1c1cef65f18c0654"},"employeeID":"KMHEC4A48BA691177","name":"Ronda Ellicock"}
{"_id":{"$oid":"9b46bbb95c6e0219074a8959"},"employeeID":"WAUDF58E85A843908","name":"Hannis Varns"}
{"_id":{"$oid":"32cf420a7cf917d6bd235338"},"employeeID":"WAUAF48H09K033213","name":"Fransisco Di Francecshi"}
{"_id":{"$oid":"e6b874e354fdac6fcade413e"},"employeeID":"137ZA90341E581044","name":"Juditha Ox"}
{"_id":{"$oid":"dcb3cfd9dc193a2b26903d72"},"employeeID":"JM1CW2BLXC0164777","name":"Beverlee Bodleigh"}
{"_id":{"$oid":"48e137e28a26b0c75395e523"},"employeeID":"WBALW3C58CC100352","name":"Vannie Breukelman"}
{"_id":{"$oid":"17e1b347683e2ee3327c9a86"},"employeeID":"3C4PDDGG7ET307429","name":"Dave Anneslie"}
{"_id":{"$oid":"f4da6a013969df9d9045b235"},"employeeID":"WAUPN44E97N676793","name":"Reamonn Ashfold"}
{"_id":{"$oid":"c6069d7027641ed2415e92c0"},"employeeID":"JN1CV6EKXBM784567","name":"Martie Ateridge"}
{"_id":{"$oid":"e218ff61229cb39a4ab65ce2"},"employeeID":"JN1AZ4EH0EM654354","name":"Karola Ferrero"}
{"_id":{"$oid":"20294fc7c2987fee9f533012"},"employeeID":"JTDKDTB32D1571205","name":"Evyn Doughton"}
{"_id":{"$oid":"c6de7dd77d88529240380763"},"employeeID":"WBA5B1C54ED236645","name":"Hayley Brouard"}
{"_id":{"$oid":"227dd4b2d1c00f27b569d2a0"},"employeeID":"YV1612FS1E1840280","name":"Tine Matsell"}
{"_id":{"$oid":"4e91a9ad68573e2867bf51f0"},"employeeID":"WBALX3C57CC804684","name":"Erie Brookesbie"}
{"_id":{"$oid":"87c840a84534de791010e4f1"},"employeeID":"2FMDK3AK4EB663504","name":"Gwynne Syce"}
